Metadata-Version: 2.1
Name: dinoxtool
Version: 1.0.0
Summary: A library for making multitools
Home-page: http://example.com/
Author: Miki007
License: UNKNOWN
Platform: UNKNOWN
Classifier: Programming Language :: Python :: 3.12
